r5py/sampledata/sao_paulo/__init__.py
r5py_sampledata_sao_paulo-1.0.3.post2.dist-info/licenses/LICENSE
r5py_sampledata_sao_paulo-1.0.3.post2.dist-info/METADATA
r5py_sampledata_sao_paulo-1.0.3.post2.dist-info/WHEEL
r5py_sampledata_sao_paulo-1.0.3.post2.dist-info/top_level.txt
r5py_sampledata_sao_paulo-1.0.3.post2.dist-info/RECORD
