Metadata-Version: 2.4
Name: r5py.sampledata.sao_paulo
Version: 1.0.3.post2
Summary: Sample data for the r5py module, covering São Paulo city centre
Author: Christoph Fink, Willem Klumpenhouwer, Marcus Sairava, Rafael Pereira, Henrikki Tenkanen
License: GPL-3.0-or-later or MIT
Project-URL: Documentation, https://r5py.readthedocs.org/
Project-URL: Repository, https://github.com/r5py/r5py.sampledata.sao_paulo.git
Project-URL: Change log, https://github.com/r5py/r5py.sampledata.sao_paulo/blob/main/CHANGELOG.md
Project-URL: Bug tracker, https://github.com/r5py/r5py.sampledata.sao_paulo/issues
Keywords: accessibility,transport,routing,research
Classifier: Programming Language :: Python :: 3
Classifier: License :: OSI Approved :: GNU General Public License v3 (GPLv3)
Classifier: License :: OSI Approved :: MIT License
Classifier: Operating System :: OS Independent
Requires-Python: >=3.10
License-File: LICENSE
Provides-Extra: tests
Requires-Dist: pytest; extra == "tests"
Requires-Dist: r5py>=0.1.0; extra == "tests"
Dynamic: license-file
